sunbear/__init__.py
sunbear/forward.py
sunbear/inverse.py
sunbear/version.py
sunbear/vis.py
sunbear/gradopt/__init__.py
sunbear/gradopt/gradopt_interface.py
sunbear/gradopt/momentum.py
sunbear/math/__init__.py
sunbear/math/_utils.py
sunbear/math/det.py
sunbear/math/diff.py
sunbear/math/test/__init__.py
sunbear/math/test/diff_test.py
sunbear/test/__init__.py
sunbear/test/forward_test.py
sunbear/test/inverse_test.py
sunbear-0.1.0.dist-info/LICENSE.txt
sunbear-0.1.0.dist-info/METADATA
sunbear-0.1.0.dist-info/WHEEL
sunbear-0.1.0.dist-info/top_level.txt
sunbear-0.1.0.dist-info/RECORD
